{
  "lastCheck": "2026-05-01T23:05:00Z",
  "agent": "KiloClaw",
  "status": "degraded",
  "uptime": "unknown",
  "workspace": "/root/.openclaw/workspace",
  "channel": "telegram",
  "runtime": {
    "agent": "main",
    "host": "48e16dec132538",
    "node": "v24.14.1",
    "model": "kilocode/stepfun/step-3.5-flash:free",
    "thinking": false
  },
  "lastContinuityRun": "2026-05-02T13:35:08.000Z",
  "nextHeartbeat": "2026-05-02T14:05:08.000Z",
  "lastChecks": {
    "continuity": "2026-05-02T13:35:08.000Z",
    "ledger": "2026-05-02T13:35:08.000Z"
  },
  "degradationReason": "coherenceScore: 0.536 (target 0.95)",
  "updatedAt": "2026-05-02T13:35:08.156Z"
}
