{
  "version": 1,
  "files": {
    "memory/2026-05-28.md": {
      "mtimeMs": 1779930111517,
      "size": 310
    },
    "memory/2026-05-27.md": {
      "mtimeMs": 1779923208884,
      "size": 1576
    },
    "memory/2026-05-26.md": {
      "mtimeMs": 1779826567437,
      "size": 547
    },
    "memory/2026-05-25.md": {
      "mtimeMs": 1779698883761,
      "size": 1158
    },
    "memory/2026-05-24.md": {
      "mtimeMs": 1779640348518,
      "size": 5513
    },
    "memory/2026-05-23.md": {
      "mtimeMs": 1779582261991,
      "size": 41802
    },
    "memory/2026-05-22.md": {
      "mtimeMs": 1779487295041,
      "size": 14568
    },
    "memory/2026-05-21.md": {
      "mtimeMs": 1779392332068,
      "size": 39341
    }
  }
}
